qutip_qtrl/__init__.py
qutip_qtrl/cy_grape.py
qutip_qtrl/dump.py
qutip_qtrl/dynamics.py
qutip_qtrl/errors.py
qutip_qtrl/family.py
qutip_qtrl/fidcomp.py
qutip_qtrl/grape.py
qutip_qtrl/io.py
qutip_qtrl/loadparams.py
qutip_qtrl/logging_utils.py
qutip_qtrl/optimconfig.py
qutip_qtrl/optimizer.py
qutip_qtrl/optimresult.py
qutip_qtrl/propcomp.py
qutip_qtrl/pulsegen.py
qutip_qtrl/pulseoptim.py
qutip_qtrl/stats.py
qutip_qtrl/symplectic.py
qutip_qtrl/termcond.py
qutip_qtrl/tslotcomp.py
qutip_qtrl/version.py
qutip_qtrl-0.1.5.dist-info/licenses/LICENSE
qutip_qtrl-0.1.5.dist-info/METADATA
qutip_qtrl-0.1.5.dist-info/WHEEL
qutip_qtrl-0.1.5.dist-info/entry_points.txt
qutip_qtrl-0.1.5.dist-info/top_level.txt
qutip_qtrl-0.1.5.dist-info/RECORD
