Metadata-Version: 2.4
Name: qutip-qtrl
Version: 0.1.5
Summary: The QuTiP quantum optimal control package
Home-page: https://github.com/qutip/qutip-qtrl
Author: Alexander Pitchford, Paul D. Nation, Robert J. Johansson, Chris Granade, Arne Grimsmo, Nathan Shammah, Shahnawaz Ahmed, Neill Lambert, Eric Giguere, Boxi Li, Jake Lishman, Simon Cross, Asier Galicia
Author-email: qutip-admin@googlegroups.com
License: BSD 3-Clause License
Keywords: quantum,physics,dynamics,optimal,control
Platform: Linux
Platform: Mac OSX
Platform: Unix
Platform: Windows
Classifier: Development Status :: 2 - Pre-Alpha
Classifier: Intended Audience :: Science/Research
Classifier: License :: OSI Approved :: BSD License
Classifier: Programming Language :: Python
Classifier: Programming Language :: Python :: 3
Classifier: Topic :: Scientific/Engineering
Classifier: Operating System :: MacOS
Classifier: Operating System :: POSIX
Classifier: Operating System :: Unix
Classifier: Operating System :: Microsoft :: Windows
License-File: LICENSE
Requires-Dist: numpy>=1.19
Requires-Dist: scipy>=1.0
Requires-Dist: qutip>=5.0.1
Requires-Dist: packaging
Provides-Extra: tests
Requires-Dist: pytest>=5.2; extra == "tests"
Provides-Extra: full
Requires-Dist: pytest>=5.2; extra == "full"
Dynamic: license-file
